[
    {
      "image": "https://i.ibb.co.com/SDWRtSvZ/e632982bae5808525ce4e321a3ad6a5e.jpg",
      "title": "Pixel Camera",
      "companyName": "Vision Labs",
      "id": 1,
      "description": "High-quality AI camera app with filters.",
      "size": 48,
      "reviews": 1200,
      "ratingAvg": 4.5,
      "downloads": 5,
      "ratings": [
        { "name": "1 star", "count": 50 },
        { "name": "2 star", "count": 70 },
        { "name": "3 star", "count": 150 },
        { "name": "4 star", "count": 300 },
        { "name": "5 star", "count": 630 }
      ]
    },
    {
      "image": "https://i.ibb.co.com/4wXS73LQ/demo-app-2.webp",
      "title": "Galaxy Shooter",
      "companyName": "StarPlay Studios",
      "id": 2,
      "description": "Arcade style galaxy combat game.",
      "size": 92,
      "reviews": 870,
      "ratingAvg": 4.1,
      "downloads": 3,
      "ratings": [
        { "name": "1 star", "count": 80 },
        { "name": "2 star", "count": 60 },
        { "name": "3 star", "count": 120 },
        { "name": "4 star", "count": 300 },
        { "name": "5 star", "count": 310 }
      ]
    },
    {
      "image": "https://i.ibb.co.com/n8mRM82B/beat-Box-Music.jpg",
      "title": "BeatBox Music",
      "companyName": "WaveSound LLC",
      "id": 3,
      "description": "Unlimited music streaming app.",
      "size": 65,
      "reviews": 5600,
      "ratingAvg": 4.7,
      "downloads": 12,
      "ratings": [
        { "name": "1 star", "count": 200 },
        { "name": "2 star", "count": 300 },
        { "name": "3 star", "count": 500 },
        { "name": "4 star", "count": 1500 },
        { "name": "5 star", "count": 3100 }
      ]
    },
    {
      "image": "https://i.ibb.co.com/fBYdbWf/light-Reader.jpg",
      "title": "LightReader",
      "companyName": "SoftTech",
      "id": 4,
      "description": "Ebook reader with dark mode.",
      "size": 24,
      "reviews": 2100,
      "ratingAvg": 4.6,
      "downloads": 7,
      "ratings": [
        { "name": "1 star", "count": 50 },
        { "name": "2 star", "count": 80 },
        { "name": "3 star", "count": 200 },
        { "name": "4 star", "count": 600 },
        { "name": "5 star", "count": 1170 }
      ]
    },
    {
      "image": "https://i.ibb.co.com/rG58GnV3/forcast.jpg",
      "title": "Sky Forecast",
      "companyName": "Weather Pro",
      "id": 5,
      "description": "Accurate 7-day weather forecast.",
      "size": 39,
      "reviews": 1450,
      "ratingAvg": 4.4,
      "downloads": 5,
      "ratings": [
        { "name": "1 star", "count": 60 },
        { "name": "2 star", "count": 100 },
        { "name": "3 star", "count": 200 },
        { "name": "4 star", "count": 450 },
        { "name": "5 star", "count": 640 }
      ]
    },
    {
      "image": "https://i.ibb.co.com/gZ7GJdjz/Fit-Track-PRO.jpg",
      "title": "FitTrack Pro",
      "companyName": "BodyBuild Inc.",
      "id": 6,
      "description": "Fitness and workout tracking app.",
      "size": 58,
      "reviews": 3900,
      "ratingAvg": 4.8,
      "downloads": 9,
      "ratings": [
        { "name": "1 star", "count": 90 },
        { "name": "2 star", "count": 110 },
        { "name": "3 star", "count": 300 },
        { "name": "4 star", "count": 900 },
        { "name": "5 star", "count": 2500 }
      ]
    },
    {
      "image": "https://i.ibb.co.com/0pXQ1vny/VPN.jpg",
      "title": "GuardVPN",
      "companyName": "CyberSafe",
      "id": 7,
      "description": "Fast and secure VPN service.",
      "size": 41,
      "reviews": 800,
      "ratingAvg": 4.2,
      "downloads": 4,
      "ratings": [
        { "name": "1 star", "count": 40 },
        { "name": "2 star", "count": 80 },
        { "name": "3 star", "count": 150 },
        { "name": "4 star", "count": 250 },
        { "name": "5 star", "count": 280 }
      ]
    },
    {
      "image": "https://i.ibb.co.com/s93NGnNS/snap-Edit.jpg",
      "title": "SnapEdit",
      "companyName": "EditPro",
      "id": 8,
      "description": "Photo editing with AI tools.",
      "size": 76,
      "reviews": 3500,
      "ratingAvg": 4.5,
      "downloads": 8,
      "ratings": [
        { "name": "1 star", "count": 120 },
        { "name": "2 star", "count": 150 },
        { "name": "3 star", "count": 300 },
        { "name": "4 star", "count": 1000 },
        { "name": "5 star", "count": 1900 }
      ]
    },
    {
      "image": "https://i.ibb.co.com/Rpfd2kV2/Lingu-Ran.jpg",
      "title": "LinguaLearn",
      "companyName": "SkillWorld",
      "id": 9,
      "description": "Learn languages with fun lessons.",
      "size": 52,
      "reviews": 920,
      "ratingAvg": 4.3,
      "downloads": 3.5,
      "ratings": [
        { "name": "1 star", "count": 50 },
        { "name": "2 star", "count": 80 },
        { "name": "3 star", "count": 210 },
        { "name": "4 star", "count": 300 },
        { "name": "5 star", "count": 280 }
      ]
    },
    {
      "image": "https://i.ibb.co.com/zhJj0Kfh/Quick-Notes.jpg",
      "title": "QuickNotes",
      "companyName": "ToolsPro",
      "id": 10,
      "description": "Minimal note-taking app.",
      "size": 18,
      "reviews": 1400,
      "ratingAvg": 4.6,
      "downloads": 6,
      "ratings": [
        { "name": "1 star", "count": 20 },
        { "name": "2 star", "count": 50 },
        { "name": "3 star", "count": 200 },
        { "name": "4 star", "count": 450 },
        { "name": "5 star", "count": 680 }
      ]
    },
    {
      "image": "https://i.ibb.co.com/gLQSG4zv/Maps.jpg",
      "title": "EasyMaps",
      "companyName": "GeoTech",
      "id": 11,
      "description": "Offline map navigation app.",
      "size": 85,
      "reviews": 2200,
      "ratingAvg": 4.3,
      "downloads": 5.4,
      "ratings": [
        { "name": "1 star", "count": 80 },
        { "name": "2 star", "count": 120 },
        { "name": "3 star", "count": 300 },
        { "name": "4 star", "count": 900 },
        { "name": "5 star", "count": 800 }
      ]
    },
    {
      "image": "https://i.ibb.co.com/zTP56T0x/Chit-Chat.jpg",
      "title": "ChitChat",
      "companyName": "SocialX",
      "id": 12,
      "description": "Secure fast messaging app.",
      "size": 45,
      "reviews": 5400,
      "ratingAvg": 4.7,
      "downloads": 1.3,
      "ratings": [
        { "name": "1 star", "count": 200 },
        { "name": "2 star", "count": 350 },
        { "name": "3 star", "count": 500 },
        { "name": "4 star", "count": 1400 },
        { "name": "5 star", "count": 2950 }
      ]
    },
    {
      "image": "https://i.ibb.co.com/DgpbFd9G/Smart-Wallet.jpg",
      "title": "SmartWallet",
      "companyName": "PayFlex",
      "id": 13,
      "description": "Online payment and wallet app.",
      "size": 39,
      "reviews": 2600,
      "ratingAvg": 4.4,
      "downloads": 9,
      "ratings": [
        { "name": "1 star", "count": 100 },
        { "name": "2 star", "count": 160 },
        { "name": "3 star", "count": 330 },
        { "name": "4 star", "count": 800 },
        { "name": "5 star", "count": 1210 }
      ]
    },
    {
      "image": "https://i.ibb.co.com/1YctbgBq/Daily-News.jpg",
      "title": "DailyNews",
      "companyName": "NewsByte",
      "id": 14,
      "description": "World news from trusted sources.",
      "size": 33,
      "reviews": 1500,
      "ratingAvg": 4.2,
      "downloads": 6.7,
      "ratings": [
        { "name": "1 star", "count": 60 },
        { "name": "2 star", "count": 120 },
        { "name": "3 star", "count": 300 },
        { "name": "4 star", "count": 500 },
        { "name": "5 star", "count": 520 }
      ]
    },
    {
      "image": "https://i.ibb.co.com/cSrwrZtG/Edu-Master.jpg",
      "title": "EduMaster",
      "companyName": "LearnPro",
      "id": 15,
      "description": "Online courses and tutorials app.",
      "size": 50,
      "reviews": 3400,
      "ratingAvg": 4.6,
      "downloads": 8.3,
      "ratings": [
        { "name": "1 star", "count": 90 },
        { "name": "2 star", "count": 120 },
        { "name": "3 star", "count": 230 },
        { "name": "4 star", "count": 900 },
        { "name": "5 star", "count": 2060 }
      ]
    },
    {
      "image": "https://i.ibb.co.com/vvQ6JRFy/Time-Planner.jpg",
      "title": "TimePlanner",
      "companyName": "PlanIt",
      "id": 16,
      "description": "Smart scheduling and reminders.",
      "size": 27,
      "reviews": 2100,
      "ratingAvg": 4.5,
      "downloads": 4.1,
      "ratings": [
        { "name": "1 star", "count": 60 },
        { "name": "2 star", "count": 70 },
        { "name": "3 star", "count": 200 },
        { "name": "4 star", "count": 800 },
        { "name": "5 star", "count": 970 }
      ]
    },
    {
      "image": "https://i.ibb.co.com/2Yhqj8G2/Calculator.jpg",
      "title": "ProCalculator",
      "companyName": "CalcHub",
      "id": 17,
      "description": "Advanced scientific calculator.",
      "size": 15,
      "reviews": 950,
      "ratingAvg": 4.7,
      "downloads": 3.7,
      "ratings": [
        { "name": "1 star", "count": 10 },
        { "name": "2 star", "count": 20 },
        { "name": "3 star", "count": 90 },
        { "name": "4 star", "count": 300 },
        { "name": "5 star", "count": 530 }
      ]
    },
    {
      "image": "https://i.ibb.co.com/d03H8ghR/Shoply.jpg",
      "title": "Shoply",
      "companyName": "EcomLab",
      "id": 18,
      "description": "Online shopping with fast delivery.",
      "size": 72,
      "reviews": 5100,
      "ratingAvg": 4.6,
      "downloads": 1.5,
      "ratings": [
        { "name": "1 star", "count": 200 },
        { "name": "2 star", "count": 300 },
        { "name": "3 star", "count": 500 },
        { "name": "4 star", "count": 1200 },
        { "name": "5 star", "count": 2900 }
      ]
    },
    {
      "image": "https://i.ibb.co.com/ksrrRqyD/Pic-Gallery.jpg",
      "title": "PicGallery",
      "companyName": "PhotoPro",
      "id": 19,
      "description": "Gallery app with cloud sync.",
      "size": 36,
      "reviews": 1300,
      "ratingAvg": 4.3,
      "downloads": 5.2,
      "ratings": [
        { "name": "1 star", "count": 50 },
        { "name": "2 star", "count": 90 },
        { "name": "3 star", "count": 250 },
        { "name": "4 star", "count": 420 },
        { "name": "5 star", "count": 490 }
      ]
    },
    {
      "image": "https://i.ibb.co.com/q3s3mxrZ/Medi-Care.jpg",
      "title": "MediCare",
      "companyName": "HealthCorp",
      "id": 20,
      "description": "Online doctor consultation app.",
      "size": 61,
      "reviews": 2400,
      "ratingAvg": 4.5,
      "downloads": 7.8,
      "ratings": [
        { "name": "1 star", "count": 70 },
        { "name": "2 star", "count": 90 },
        { "name": "3 star", "count": 300 },
        { "name": "4 star", "count": 900 },
        { "name": "5 star", "count": 1040 }
      ]
    }
  ]
  